stepcount/__init__.py
stepcount/_version.py
stepcount/features.py
stepcount/hmm_utils.py
stepcount/models.py
stepcount/sslmodel.py
stepcount/stepcount.py
stepcount/utils.py
stepcount/cli_utils/__init__.py
stepcount/cli_utils/collate_outputs.py
stepcount/cli_utils/generate_commands.py
stepcount-3.17.1.dist-info/licenses/LICENSE.md
stepcount-3.17.1.dist-info/METADATA
stepcount-3.17.1.dist-info/WHEEL
stepcount-3.17.1.dist-info/entry_points.txt
stepcount-3.17.1.dist-info/top_level.txt
stepcount-3.17.1.dist-info/RECORD
