Metadata-Version: 2.4
Name: stepcount
Version: 3.17.1
Summary: Step counter for wrist-worn accelerometers compatible with the UK Biobank Accelerometer Dataset
Home-page: https://github.com/OxWearables/stepcount
Download-URL: https://github.com/OxWearables/stepcount
Author: Shing Chan, Scott Small, Gert Mertes, Aiden Doherty
Maintainer: Shing Chan
Maintainer-email: shing.chan@ndph.ox.ac.uk
License: See LICENSE file.
Classifier: Programming Language :: Python :: 3
Classifier: Topic :: Scientific/Engineering
Classifier: Topic :: Scientific/Engineering :: Bio-Informatics
Classifier: Topic :: Scientific/Engineering :: Information Analysis
Classifier: Topic :: Scientific/Engineering :: Medical Science Apps.
Requires-Python: >=3.8, <3.11
License-File: LICENSE.md
Requires-Dist: actipy>=3.8.0
Requires-Dist: numpy==1.24.*
Requires-Dist: scipy==1.10.*
Requires-Dist: pandas==2.0.*
Requires-Dist: tqdm==4.64.*
Requires-Dist: joblib==1.2.*
Requires-Dist: scikit-learn==1.1.1
Requires-Dist: imbalanced-learn==0.9.1
Requires-Dist: hmmlearn==0.3.*
Requires-Dist: torch==1.13.*
Requires-Dist: torchvision==0.14.*
Requires-Dist: transforms3d==0.4.*
Requires-Dist: numba==0.58.*
Requires-Dist: matplotlib==3.7.*
Provides-Extra: dev
Requires-Dist: flake8; extra == "dev"
Requires-Dist: autopep8; extra == "dev"
Requires-Dist: ipython; extra == "dev"
Requires-Dist: ipdb; extra == "dev"
Requires-Dist: twine; extra == "dev"
Requires-Dist: tomli; extra == "dev"
Requires-Dist: jupyter; extra == "dev"
Requires-Dist: matplotlib; extra == "dev"
Requires-Dist: pytest>=7.0; extra == "dev"
Requires-Dist: pytest-cov>=4.0; extra == "dev"
Provides-Extra: docs
Requires-Dist: sphinx>=4.2; extra == "docs"
Requires-Dist: sphinx_rtd_theme>=1.0; extra == "docs"
Requires-Dist: readthedocs-sphinx-search>=0.1; extra == "docs"
Requires-Dist: sphinxcontrib-programoutput>=0.17; extra == "docs"
Requires-Dist: docutils<0.18; extra == "docs"
Dynamic: author
Dynamic: classifier
Dynamic: description
Dynamic: description-content-type
Dynamic: download-url
Dynamic: home-page
Dynamic: license
Dynamic: license-file
Dynamic: maintainer
Dynamic: maintainer-email
Dynamic: provides-extra
Dynamic: requires-dist
Dynamic: requires-python
Dynamic: summary
